{
  "description": "Mit diesem BO werden die Fremdkosten, beispielsweise für eine Angebotserstellung oder eine Rechnungsprüfung,\nübertragen.\nDie Fremdkosten enthalten dabei alle Kostenblöcke, die von anderen Marktteilnehmern oder Instanzen erhoben werden.\n\n.. raw:: html\n\n    <object data=\"../_static/images/bo4e/bo/Fremdkosten.svg\" type=\"image/svg+xml\"></object>\n\n.. HINT::\n    `Fremdkosten JSON Schema <https://json-schema.app/view/%23?url=https://raw.githubusercontent.com/Hochfrequenz/BO4E-Schemas/v202401.0.0-/src/bo4e_schemas/bo/Fremdkosten.json>`_",
  "title": "Fremdkosten",
  "type": "object",
  "additionalProperties": true,
  "properties": {
    "_id": {
      "title": " Id",
      "default": null,
      "anyOf": [
        {
          "type": "string"
        },
        {
          "type": "null"
        }
      ]
    },
    "_typ": {
      "default": "FREMDKOSTEN",
      "anyOf": [
        {
          "$ref": "../enum/Typ.json#"
        },
        {
          "type": "null"
        }
      ]
    },
    "_version": {
      "title": " Version",
      "default": "v202401.0.0",
      "anyOf": [
        {
          "type": "string"
        },
        {
          "type": "null"
        }
      ]
    },
    "gueltigkeit": {
      "default": null,
      "anyOf": [
        {
          "$ref": "../com/Zeitraum.json#"
        },
        {
          "type": "null"
        }
      ]
    },
    "kostenbloecke": {
      "title": "Kostenbloecke",
      "default": null,
      "anyOf": [
        {
          "type": "array",
          "items": {
            "$ref": "../com/Fremdkostenblock.json#"
          }
        },
        {
          "type": "null"
        }
      ]
    },
    "summeKosten": {
      "default": null,
      "anyOf": [
        {
          "$ref": "../com/Betrag.json#"
        },
        {
          "type": "null"
        }
      ]
    },
    "zusatzAttribute": {
      "title": "Zusatzattribute",
      "default": null,
      "anyOf": [
        {
          "type": "array",
          "items": {
            "$ref": "https://raw.githubusercontent.com/Hochfrequenz/BO4E-Schemas/v202401.0.0/src/bo4e_schemas/ZusatzAttribut.json"
          }
        },
        {
          "type": "null"
        }
      ]
    }
  }
}