{
    "additionalProperties": true,
    "description": "Contains an address that can be used for most purposes.\n\n.. raw:: html\n\n    <object data=\"../_static/images/bo4e/com/Adresse.svg\" type=\"image/svg+xml\"></object>\n\n.. HINT::\n    `Adresse JSON Schema <https://json-schema.app/view/%23?url=https://raw.githubusercontent.com/Hochfrequenz/BO4E-Schemas/v202401.0.0-/src/bo4e_schemas/com/Adresse.json>`_",
    "properties": {
        "_id": {
            "anyOf": [
                {
                    "type": "string"
                },
                {
                    "type": "null"
                }
            ],
            "default": null,
            "title": " Id"
        },
        "_version": {
            "anyOf": [
                {
                    "type": "string"
                },
                {
                    "type": "null"
                }
            ],
            "default": "202401.0.0",
            "title": " Version"
        },
        "adresszusatz": {
            "anyOf": [
                {
                    "type": "string"
                },
                {
                    "type": "null"
                }
            ],
            "default": null,
            "title": "Adresszusatz"
        },
        "coErgaenzung": {
            "anyOf": [
                {
                    "type": "string"
                },
                {
                    "type": "null"
                }
            ],
            "default": null,
            "title": "Coergaenzung"
        },
        "hausnummer": {
            "anyOf": [
                {
                    "type": "string"
                },
                {
                    "type": "null"
                }
            ],
            "default": null,
            "title": "Hausnummer"
        },
        "landescode": {
            "anyOf": [
                {
                    "$ref": "https://raw.githubusercontent.com/Hochfrequenz/BO4E-Schemas/v202401.0.0/src/bo4e_schemas/enum/Landescode.json"
                },
                {
                    "type": "null"
                }
            ],
            "default": "DE"
        },
        "ort": {
            "anyOf": [
                {
                    "type": "string"
                },
                {
                    "type": "null"
                }
            ],
            "default": null,
            "title": "Ort"
        },
        "ortsteil": {
            "anyOf": [
                {
                    "type": "string"
                },
                {
                    "type": "null"
                }
            ],
            "default": null,
            "title": "Ortsteil"
        },
        "postfach": {
            "anyOf": [
                {
                    "type": "string"
                },
                {
                    "type": "null"
                }
            ],
            "default": null,
            "title": "Postfach"
        },
        "postleitzahl": {
            "anyOf": [
                {
                    "type": "string"
                },
                {
                    "type": "null"
                }
            ],
            "default": null,
            "title": "Postleitzahl"
        },
        "strasse": {
            "anyOf": [
                {
                    "type": "string"
                },
                {
                    "type": "null"
                }
            ],
            "default": null,
            "title": "Strasse"
        },
        "zusatzAttribute": {
            "anyOf": [
                {
                    "items": {
                        "$ref": "https://raw.githubusercontent.com/Hochfrequenz/BO4E-Schemas/v202401.0.0/src/bo4e_schemas/ZusatzAttribut.json"
                    },
                    "type": "array"
                },
                {
                    "type": "null"
                }
            ],
            "default": null,
            "title": "Zusatzattribute"
        }
    },
    "title": "Adresse",
    "type": "object"
}
